{
  "items": [
    {
      "id": "OMkEVX23BdM",
      "link": "https://www.youtube.com/watch?v=OMkEVX23BdM",
      "kind": "youtube#video",
      "publishedAt": "2017-12-16T17:00:02Z",
      "channelId": "UCDPk9MG2RexnOMGTD-YnSnA",
      "channelTitle": "Nat Geo WILD",
      "title": "Lions 101 | Nat Geo Wild",
      "description": "#NatGeoWILD #Lions #Educational About National Geographic Wild: National Geographic Wild is a place for all things animals and for animal-lovers alike.",
      "thumbnails": {
        "default": {
          "url": "https://i.ytimg.com/vi/OMkEVX23BdM/default.jpg",
          "width": 120,
          "height": 90
        },
        "medium": {
          "url": "https://i.ytimg.com/vi/OMkEVX23BdM/mqdefault.jpg",
          "width": 320,
          "height": 180
        },
        "high": {
          "url": "https://i.ytimg.com/vi/OMkEVX23BdM/hqdefault.jpg",
          "width": 480,
          "height": 360
        }
      }
    },
    {
      "id": "dJU9ZkPorDE",
      "link": "https://www.youtube.com/watch?v=dJU9ZkPorDE",
      "kind": "youtube#video",
      "publishedAt": "2020-05-28T18:38:16Z",
      "channelId": "UCOo7zhYE_xeVyXkcL7XVg0w",
      "channelTitle": "Amazing Documentaries",
      "title": "WHEN LIONS ATTACK *BRUTAL* National Geographic Documentary 2020 | 1080p",
      "description": "WHAT TO DO IF YOU ARE ATTACKED BY A LION: Being charged by a lion when you are on foot is extremely frightening. It is difficult to stop yourself from ...",
      "thumbnails": {
        "default": {
          "url": "https://i.ytimg.com/vi/dJU9ZkPorDE/default.jpg",
          "width": 120,
          "height": 90
        },
        "medium": {
          "url": "https://i.ytimg.com/vi/dJU9ZkPorDE/mqdefault.jpg",
          "width": 320,
          "height": 180
        },
        "high": {
          "url": "https://i.ytimg.com/vi/dJU9ZkPorDE/hqdefault.jpg",
          "width": 480,
          "height": 360
        }
      }
    },
    {
      "id": "4dzj5rEFAdk",
      "link": "https://www.youtube.com/watch?v=4dzj5rEFAdk",
      "kind": "youtube#video",
      "publishedAt": "2020-09-26T13:08:53Z",
      "channelId": "UCz73YrQjemoqx6ZvVfJDAew",
      "channelTitle": "Free Documentary - Animals",
      "title": "The Strongest LION PRIDE in Luangwa Valley - National Geographic Documentary 2020 (Full HD 1080p)",
      "description": "The Strongest LION PRIDE in Luangwa Valley - National Geographic Wild Documentary 2020 (HD 1080p). Check our Patreon for exclusive content: ...",
      "thumbnails": {
        "default": {
          "url": "https://i.ytimg.com/vi/4dzj5rEFAdk/default.jpg",
          "width": 120,
          "height": 90
        },
        "medium": {
          "url": "https://i.ytimg.com/vi/4dzj5rEFAdk/mqdefault.jpg",
          "width": 320,
          "height": 180
        },
        "high": {
          "url": "https://i.ytimg.com/vi/4dzj5rEFAdk/hqdefault.jpg",
          "width": 480,
          "height": 360
        }
      }
    },
    {
      "id": "jenVMnOi2uA",
      "link": "https://www.youtube.com/watch?v=jenVMnOi2uA",
      "kind": "youtube#video",
      "publishedAt": "2020-03-01T12:48:36Z",
      "channelId": "UCIsz3XD8_E1ebhE4YScWeJg",
      "channelTitle": "Dean Schneider",
      "title": "Part of the Lion Pride - Dean Schneider living with lions",
      "description": "One of the most common questions I am asked is how I achieved to become part of a Lion Pride and how do I manage to be so close with them in every situation.",
      "thumbnails": {
        "default": {
          "url": "https://i.ytimg.com/vi/jenVMnOi2uA/default.jpg",
          "width": 120,
          "height": 90
        },
        "medium": {
          "url": "https://i.ytimg.com/vi/jenVMnOi2uA/mqdefault.jpg",
          "width": 320,
          "height": 180
        },
        "high": {
          "url": "https://i.ytimg.com/vi/jenVMnOi2uA/hqdefault.jpg",
          "width": 480,
          "height": 360
        }
      }
    },
    {
      "id": "dKg4WZWVxEU",
      "link": "https://www.youtube.com/watch?v=dKg4WZWVxEU",
      "kind": "youtube#video",
      "publishedAt": "2020-07-28T04:44:43Z",
      "channelId": "UCsKhFZ5zY5DEUSZnh_xhHPA",
      "channelTitle": "Home",
      "title": "Lions (Nature Documentary)",
      "description": "Lions (Nature Documentary) Donate: https://www.paypal.me/HomeChannel Thank You for support!!",
      "thumbnails": {
        "default": {
          "url": "https://i.ytimg.com/vi/dKg4WZWVxEU/default.jpg",
          "width": 120,
          "height": 90
        },
        "medium": {
          "url": "https://i.ytimg.com/vi/dKg4WZWVxEU/mqdefault.jpg",
          "width": 320,
          "height": 180
        },
        "high": {
          "url": "https://i.ytimg.com/vi/dKg4WZWVxEU/hqdefault.jpg",
          "width": 480,
          "height": 360
        }
      }
    },
    {
      "id": "Z8hI5uqpy_w",
      "link": "https://www.youtube.com/watch?v=Z8hI5uqpy_w",
      "kind": "youtube#video",
      "publishedAt": "2020-03-03T17:00:12Z",
      "channelId": "UCwmZiChSryoWQCZMIQezgTg",
      "channelTitle": "BBC Earth",
      "title": "Best Lion Moments: Part 1 | Top 5 | BBC Earth",
      "description": "#BestOfLions #DavidAttenborough #BBCEarth Watch more: Planet Earth http://bit.ly/PlanetEarthPlaylist Blue Planet http://bit.ly/BluePlanetPlaylist Planet Earth II ...",
      "thumbnails": {
        "default": {
          "url": "https://i.ytimg.com/vi/Z8hI5uqpy_w/default.jpg",
          "width": 120,
          "height": 90
        },
        "medium": {
          "url": "https://i.ytimg.com/vi/Z8hI5uqpy_w/mqdefault.jpg",
          "width": 320,
          "height": 180
        },
        "high": {
          "url": "https://i.ytimg.com/vi/Z8hI5uqpy_w/hqdefault.jpg",
          "width": 480,
          "height": 360
        }
      }
    },
    {
      "id": "uFcZhH_wFbs",
      "link": "https://www.youtube.com/watch?v=uFcZhH_wFbs",
      "kind": "youtube#video",
      "publishedAt": "2018-08-03T18:23:44Z",
      "channelId": "UCF1nEd0lin1hGtvSZOBPnsg",
      "channelTitle": "Stripy Yoshi",
      "title": "Lions Roaring Compilation",
      "description": "A compilation of all of the Lions that I have seen and recorded roaring in zoos! Zoos Included: San Diego Zoo ZSL London Zoo Cotswold Wildlife Park Yorkshire ...",
      "thumbnails": {
        "default": {
          "url": "https://i.ytimg.com/vi/uFcZhH_wFbs/default.jpg",
          "width": 120,
          "height": 90
        },
        "medium": {
          "url": "https://i.ytimg.com/vi/uFcZhH_wFbs/mqdefault.jpg",
          "width": 320,
          "height": 180
        },
        "high": {
          "url": "https://i.ytimg.com/vi/uFcZhH_wFbs/hqdefault.jpg",
          "width": 480,
          "height": 360
        }
      }
    },
    {
      "id": "Uy3o5RyU-gs",
      "link": "https://www.youtube.com/watch?v=Uy3o5RyU-gs",
      "kind": "youtube#video",
      "publishedAt": "2020-10-20T09:01:24Z",
      "channelId": "UCyfZleh4w7buTzi0WfY8WqA",
      "channelTitle": "Kruger Sightings",
      "title": "3 Lions Corner Buffalo With Broken Leg",
      "description": "He shared the sighting of 3 male lions taking down a female buffalo and excitedly told LatestSightings.com that this was one of, if not, the best, sighting he ever ...",
      "thumbnails": {
        "default": {
          "url": "https://i.ytimg.com/vi/Uy3o5RyU-gs/default.jpg",
          "width": 120,
          "height": 90
        },
        "medium": {
          "url": "https://i.ytimg.com/vi/Uy3o5RyU-gs/mqdefault.jpg",
          "width": 320,
          "height": 180
        },
        "high": {
          "url": "https://i.ytimg.com/vi/Uy3o5RyU-gs/hqdefault.jpg",
          "width": 480,
          "height": 360
        }
      }
    },
    {
      "id": "d-ubU5QPK4g",
      "link": "https://www.youtube.com/watch?v=d-ubU5QPK4g",
      "kind": "youtube#video",
      "publishedAt": "2020-09-17T16:36:13Z",
      "channelId": "UCz73YrQjemoqx6ZvVfJDAew",
      "channelTitle": "Free Documentary - Animals",
      "title": "Lion Pride 2020 -  Working Together To Survive | National Geographic Documentary HD (Wild Life)",
      "description": "National Geographic Documentary Video about Nsefu Lions Pride Surviving on Luangwa Valley. National Geographic Wild Documentary 2020 Full Hd 1080p.",
      "thumbnails": {
        "default": {
          "url": "https://i.ytimg.com/vi/d-ubU5QPK4g/default.jpg",
          "width": 120,
          "height": 90
        },
        "medium": {
          "url": "https://i.ytimg.com/vi/d-ubU5QPK4g/mqdefault.jpg",
          "width": 320,
          "height": 180
        },
        "high": {
          "url": "https://i.ytimg.com/vi/d-ubU5QPK4g/hqdefault.jpg",
          "width": 480,
          "height": 360
        }
      }
    },
    {
      "id": "5J3ZqKHoh0w",
      "link": "https://www.youtube.com/watch?v=5J3ZqKHoh0w",
      "kind": "youtube#video",
      "publishedAt": "2020-08-31T17:40:40Z",
      "channelId": "UCRZPkuHwaoKwTP3CYPdVldg",
      "channelTitle": "Love Nature",
      "title": "Baby Lions Meet Dad For The First Time | Love Nature",
      "description": "A couple of cute lion cubs meet their dad for the first time when the cubs' father rejoins the pride. These cubs left their den six months after they were born in ...",
      "thumbnails": {
        "default": {
          "url": "https://i.ytimg.com/vi/5J3ZqKHoh0w/default.jpg",
          "width": 120,
          "height": 90
        },
        "medium": {
          "url": "https://i.ytimg.com/vi/5J3ZqKHoh0w/mqdefault.jpg",
          "width": 320,
          "height": 180
        },
        "high": {
          "url": "https://i.ytimg.com/vi/5J3ZqKHoh0w/hqdefault.jpg",
          "width": 480,
          "height": 360
        }
      }
    },
    {
      "id": "9c3d8BnTxHM",
      "link": "https://www.youtube.com/watch?v=9c3d8BnTxHM",
      "kind": "youtube#video",
      "publishedAt": "2020-09-14T17:09:38Z",
      "channelId": "UCz73YrQjemoqx6ZvVfJDAew",
      "channelTitle": "Free Documentary - Animals",
      "title": "Lion Documentary - New Generation, Will They Survive? - Wild Life 2020 Full HD 1080p",
      "description": "Lionesses of Nsefu Pride are having a hard time defending their newly born cubs from enemies. The cubs must survive for their pride's future. National ...",
      "thumbnails": {
        "default": {
          "url": "https://i.ytimg.com/vi/9c3d8BnTxHM/default.jpg",
          "width": 120,
          "height": 90
        },
        "medium": {
          "url": "https://i.ytimg.com/vi/9c3d8BnTxHM/mqdefault.jpg",
          "width": 320,
          "height": 180
        },
        "high": {
          "url": "https://i.ytimg.com/vi/9c3d8BnTxHM/hqdefault.jpg",
          "width": 480,
          "height": 360
        }
      }
    },
    {
      "id": "4oavOSGo39w",
      "link": "https://www.youtube.com/watch?v=4oavOSGo39w",
      "kind": "youtube#video",
      "publishedAt": "2020-09-09T13:59:44Z",
      "channelId": "UCz73YrQjemoqx6ZvVfJDAew",
      "channelTitle": "Free Documentary - Animals",
      "title": "Wild Life - Lion Pride Documentary 2020 Full HD 1080p",
      "description": "National Geographic Documentary about Nsefu Lions Pride Surviving in Luangwa Valley. Pretadors Wild Life 2020 Full HD 1080p. Check our Patreon for ...",
      "thumbnails": {
        "default": {
          "url": "https://i.ytimg.com/vi/4oavOSGo39w/default.jpg",
          "width": 120,
          "height": 90
        },
        "medium": {
          "url": "https://i.ytimg.com/vi/4oavOSGo39w/mqdefault.jpg",
          "width": 320,
          "height": 180
        },
        "high": {
          "url": "https://i.ytimg.com/vi/4oavOSGo39w/hqdefault.jpg",
          "width": 480,
          "height": 360
        }
      }
    },
    {
      "id": "8O9q8zCIf2o",
      "link": "https://www.youtube.com/watch?v=8O9q8zCIf2o",
      "kind": "youtube#video",
      "publishedAt": "2021-02-14T12:00:08Z",
      "channelId": "UC91_dGVjroS9CJfq8VlB9Ew",
      "channelTitle": "BUZZBIBLE VIDÉO",
      "title": "A Lion Chews a Baboon to Punish him for Stealing his Cub [ Unreal story ]",
      "description": "Note : This content is mixed between fact and fiction. Sometimes we create fictional stories, where we combine a few clips to create an educational story for the ...",
      "thumbnails": {
        "default": {
          "url": "https://i.ytimg.com/vi/8O9q8zCIf2o/default.jpg",
          "width": 120,
          "height": 90
        },
        "medium": {
          "url": "https://i.ytimg.com/vi/8O9q8zCIf2o/mqdefault.jpg",
          "width": 320,
          "height": 180
        },
        "high": {
          "url": "https://i.ytimg.com/vi/8O9q8zCIf2o/hqdefault.jpg",
          "width": 480,
          "height": 360
        }
      }
    },
    {
      "id": "5YU4lLxi0go",
      "link": "https://www.youtube.com/watch?v=5YU4lLxi0go",
      "kind": "youtube#video",
      "publishedAt": "2019-08-13T23:00:00Z",
      "channelId": "UC9LxuffQCm_Z4KBCoXZvSHA",
      "channelTitle": "Beastly",
      "title": "The Man Who Cuddles Lions | BEAST BUDDIES",
      "description": "MEET the daring animal lover who spends his days cuddling tigers and playing football with a pride of lions. Armand Gerber, 51, runs the Iron Throne Predator ...",
      "thumbnails": {
        "default": {
          "url": "https://i.ytimg.com/vi/5YU4lLxi0go/default.jpg",
          "width": 120,
          "height": 90
        },
        "medium": {
          "url": "https://i.ytimg.com/vi/5YU4lLxi0go/mqdefault.jpg",
          "width": 320,
          "height": 180
        },
        "high": {
          "url": "https://i.ytimg.com/vi/5YU4lLxi0go/hqdefault.jpg",
          "width": 480,
          "height": 360
        }
      }
    },
    {
      "id": "t6Y7yQIZT4Q",
      "link": "https://www.youtube.com/watch?v=t6Y7yQIZT4Q",
      "kind": "youtube#video",
      "publishedAt": "2017-02-03T05:00:03Z",
      "channelId": "UCD_pT-Ky5AtHdvhAg20GAew",
      "channelTitle": "SkipMarleyVEVO",
      "title": "Skip Marley - Lions (Lyric Video)",
      "description": "Music video by Skip Marley performing Lions. (C) 2017 Island Records, a division of UMG Recordings, Inc. http://vevo.ly/8QdIjK Playlist Best of Skip Marley ...",
      "thumbnails": {
        "default": {
          "url": "https://i.ytimg.com/vi/t6Y7yQIZT4Q/default.jpg",
          "width": 120,
          "height": 90
        },
        "medium": {
          "url": "https://i.ytimg.com/vi/t6Y7yQIZT4Q/mqdefault.jpg",
          "width": 320,
          "height": 180
        },
        "high": {
          "url": "https://i.ytimg.com/vi/t6Y7yQIZT4Q/hqdefault.jpg",
          "width": 480,
          "height": 360
        }
      }
    },
    {
      "id": "j-GP3p1x5MY",
      "link": "https://www.youtube.com/watch?v=j-GP3p1x5MY",
      "kind": "youtube#video",
      "publishedAt": "2020-08-26T14:00:11Z",
      "channelId": "UCTTQAOiR_0DuyQPZ6Dg-LHA",
      "channelTitle": "Talltanic",
      "title": "8 Most Unique Lions On Earth",
      "description": "From lions with practically mythological features to some you may have never heard of, here are 8 of the most unique lions in the world. Subscribe to Talltanic: ...",
      "thumbnails": {
        "default": {
          "url": "https://i.ytimg.com/vi/j-GP3p1x5MY/default.jpg",
          "width": 120,
          "height": 90
        },
        "medium": {
          "url": "https://i.ytimg.com/vi/j-GP3p1x5MY/mqdefault.jpg",
          "width": 320,
          "height": 180
        },
        "high": {
          "url": "https://i.ytimg.com/vi/j-GP3p1x5MY/hqdefault.jpg",
          "width": 480,
          "height": 360
        }
      }
    },
    {
      "id": "yoecv7Noq1A",
      "link": "https://www.youtube.com/watch?v=yoecv7Noq1A",
      "kind": "youtube#video",
      "publishedAt": "2019-05-30T21:00:10Z",
      "channelId": "UCUVa51UA_690sEKyRbHb-5A",
      "channelTitle": "The Finest",
      "title": "10 Most Unique Lions in the World!",
      "description": "For copyright matters please contact us: OfficialAmerikano@hotmail.com ▻ FOLLOW US ON TWITTER: https://twitter.com/Top5sFinest ▻ LIKE US ON ...",
      "thumbnails": {
        "default": {
          "url": "https://i.ytimg.com/vi/yoecv7Noq1A/default.jpg",
          "width": 120,
          "height": 90
        },
        "medium": {
          "url": "https://i.ytimg.com/vi/yoecv7Noq1A/mqdefault.jpg",
          "width": 320,
          "height": 180
        },
        "high": {
          "url": "https://i.ytimg.com/vi/yoecv7Noq1A/hqdefault.jpg",
          "width": 480,
          "height": 360
        }
      }
    },
    {
      "id": "CEDU4qBSuX0",
      "link": "https://www.youtube.com/watch?v=CEDU4qBSuX0",
      "kind": "youtube#video",
      "publishedAt": "2020-09-29T17:50:35Z",
      "channelId": "UCz73YrQjemoqx6ZvVfJDAew",
      "channelTitle": "Free Documentary - Animals",
      "title": "Wildlife - Lion Pride Wild Documentary 2020 (Nat Geo HD 1080p)",
      "description": "Nsefu lions - Misfit, a teenager with a difficult childhood. Wild Life - Lion Pride National Geographic Documentary 2020 HD 1080p. Check our Patreon for ...",
      "thumbnails": {
        "default": {
          "url": "https://i.ytimg.com/vi/CEDU4qBSuX0/default.jpg",
          "width": 120,
          "height": 90
        },
        "medium": {
          "url": "https://i.ytimg.com/vi/CEDU4qBSuX0/mqdefault.jpg",
          "width": 320,
          "height": 180
        },
        "high": {
          "url": "https://i.ytimg.com/vi/CEDU4qBSuX0/hqdefault.jpg",
          "width": 480,
          "height": 360
        }
      }
    },
    {
      "id": "n4o5r9DEhi8",
      "link": "https://www.youtube.com/watch?v=n4o5r9DEhi8",
      "kind": "youtube#video",
      "publishedAt": "2021-02-26T16:00:32Z",
      "channelId": "UC_NS4MiiHAFo3CYI7fRSLtQ",
      "channelTitle": "The Lion Whisperer",
      "title": "Who Knew Lions Could Front Flip? | The Lion Whisperer",
      "description": "Who Knew Lions Could Front Flip? | The Lion Whisperer. Kevin Richardson takes lions Vayetse, Livy and Ginny out for an enrichment walk and it's nothing like ...",
      "thumbnails": {
        "default": {
          "url": "https://i.ytimg.com/vi/n4o5r9DEhi8/default.jpg",
          "width": 120,
          "height": 90
        },
        "medium": {
          "url": "https://i.ytimg.com/vi/n4o5r9DEhi8/mqdefault.jpg",
          "width": 320,
          "height": 180
        },
        "high": {
          "url": "https://i.ytimg.com/vi/n4o5r9DEhi8/hqdefault.jpg",
          "width": 480,
          "height": 360
        }
      }
    },
    {
      "id": "VetPVhMd650",
      "link": "https://www.youtube.com/watch?v=VetPVhMd650",
      "kind": "youtube#video",
      "publishedAt": "2021-02-19T16:00:23Z",
      "channelId": "UC_NS4MiiHAFo3CYI7fRSLtQ",
      "channelTitle": "The Lion Whisperer",
      "title": "Why Lions Get Grumpy | The Lion Whisperer",
      "description": "Why Lions Get Grumpy | The Lion Whisperer. In today's video, Kevin Richardson was going to feature the lion Thor in our popular series 'The One and Only' but ...",
      "thumbnails": {
        "default": {
          "url": "https://i.ytimg.com/vi/VetPVhMd650/default.jpg",
          "width": 120,
          "height": 90
        },
        "medium": {
          "url": "https://i.ytimg.com/vi/VetPVhMd650/mqdefault.jpg",
          "width": 320,
          "height": 180
        },
        "high": {
          "url": "https://i.ytimg.com/vi/VetPVhMd650/hqdefault.jpg",
          "width": 480,
          "height": 360
        }
      }
    },
    {
      "id": "gCagvIQ1EaA",
      "link": "https://www.youtube.com/watch?v=gCagvIQ1EaA",
      "kind": "youtube#video",
      "publishedAt": "2020-11-02T14:31:51Z",
      "channelId": "UCz73YrQjemoqx6ZvVfJDAew",
      "channelTitle": "Free Documentary - Animals",
      "title": "Two Lion Prides - Who Will Come out on Top? | National Geograhpic Documentary HD",
      "description": "Two Lion Prides - Who Will Come out on Top? | National Geographic Documentary HD. Check our Patreon for exclusive content: ...",
      "thumbnails": {
        "default": {
          "url": "https://i.ytimg.com/vi/gCagvIQ1EaA/default.jpg",
          "width": 120,
          "height": 90
        },
        "medium": {
          "url": "https://i.ytimg.com/vi/gCagvIQ1EaA/mqdefault.jpg",
          "width": 320,
          "height": 180
        },
        "high": {
          "url": "https://i.ytimg.com/vi/gCagvIQ1EaA/hqdefault.jpg",
          "width": 480,
          "height": 360
        }
      }
    },
    {
      "id": "rMs06PfdJlU",
      "link": "https://www.youtube.com/watch?v=rMs06PfdJlU",
      "kind": "youtube#video",
      "publishedAt": "2020-05-23T18:20:28Z",
      "channelId": "UCfGLwxYDLZOj_eJOcMboY_A",
      "channelTitle": "ViralBe",
      "title": "Lion VS Tiger -  Who will win in a fight ?",
      "description": "Lions and tigers are among the most ferocious animals but there are important differences between them. They are both among the five big cats and are apex ...",
      "thumbnails": {
        "default": {
          "url": "https://i.ytimg.com/vi/rMs06PfdJlU/default.jpg",
          "width": 120,
          "height": 90
        },
        "medium": {
          "url": "https://i.ytimg.com/vi/rMs06PfdJlU/mqdefault.jpg",
          "width": 320,
          "height": 180
        },
        "high": {
          "url": "https://i.ytimg.com/vi/rMs06PfdJlU/hqdefault.jpg",
          "width": 480,
          "height": 360
        }
      }
    },
    {
      "id": "rnyMEVG-RWE",
      "link": "https://www.youtube.com/watch?v=rnyMEVG-RWE",
      "kind": "youtube#video",
      "publishedAt": "2019-07-17T02:11:12Z",
      "channelId": "UC5TOZ_2tjy7yfrsPH9ta6WA",
      "channelTitle": "Wild Beasts",
      "title": "Lion Documentary HD 720p Nat Geo Documentaries New",
      "description": "Filmed in the Phinda (South Africa) we follow a pride of lions over a period of time. Watch how the lions hunt, survive and protect their territory in Lion ...",
      "thumbnails": {
        "default": {
          "url": "https://i.ytimg.com/vi/rnyMEVG-RWE/default.jpg",
          "width": 120,
          "height": 90
        },
        "medium": {
          "url": "https://i.ytimg.com/vi/rnyMEVG-RWE/mqdefault.jpg",
          "width": 320,
          "height": 180
        },
        "high": {
          "url": "https://i.ytimg.com/vi/rnyMEVG-RWE/hqdefault.jpg",
          "width": 480,
          "height": 360
        }
      }
    },
    {
      "id": "CIOGjR6Z7hY",
      "link": "https://www.youtube.com/watch?v=CIOGjR6Z7hY",
      "kind": "youtube#video",
      "publishedAt": "2021-03-02T09:00:03Z",
      "channelId": "UCFQLMehakM5R2vJ_QPuWsRA",
      "channelTitle": "ТАЙГАН и МЫ",
      "title": "Раз гиена, два гиена - полосатые Лена с Геной. Тайган. Lions life in Taigan.",
      "description": "#Тайган #animals #lion.",
      "thumbnails": {
        "default": {
          "url": "https://i.ytimg.com/vi/CIOGjR6Z7hY/default.jpg",
          "width": 120,
          "height": 90
        },
        "medium": {
          "url": "https://i.ytimg.com/vi/CIOGjR6Z7hY/mqdefault.jpg",
          "width": 320,
          "height": 180
        },
        "high": {
          "url": "https://i.ytimg.com/vi/CIOGjR6Z7hY/hqdefault.jpg",
          "width": 480,
          "height": 360
        }
      }
    }
  ]
}
